pandoc_embedz/__init__.py
pandoc_embedz/config.py
pandoc_embedz/data_loader.py
pandoc_embedz/filter.py
pandoc_embedz/main.py
pandoc_embedz-0.17.0.dist-info/licenses/LICENSE
pandoc_embedz-0.17.0.dist-info/METADATA
pandoc_embedz-0.17.0.dist-info/WHEEL
pandoc_embedz-0.17.0.dist-info/entry_points.txt
pandoc_embedz-0.17.0.dist-info/top_level.txt
pandoc_embedz-0.17.0.dist-info/RECORD
