Metadata-Version: 2.4
Name: pandoc-embedz
Version: 0.17.0
Summary: Pandoc filter for embedding data-driven content using Jinja2 templates
Author: Kazumasa Utashiro
License: MIT
Project-URL: Homepage, https://github.com/tecolicom/pandoc-embedz
Project-URL: Documentation, https://github.com/tecolicom/pandoc-embedz#readme
Project-URL: Repository, https://github.com/tecolicom/pandoc-embedz
Project-URL: Issues, https://github.com/tecolicom/pandoc-embedz/issues
Keywords: pandoc,filter,jinja2,data,template,markdown
Classifier: Development Status :: 4 - Beta
Classifier: Intended Audience :: Developers
Classifier: Intended Audience :: Science/Research
Classifier: Programming Language :: Python :: 3
Classifier: Programming Language :: Python :: 3.8
Classifier: Programming Language :: Python :: 3.9
Classifier: Programming Language :: Python :: 3.10
Classifier: Programming Language :: Python :: 3.11
Classifier: Programming Language :: Python :: 3.12
Classifier: Programming Language :: Python :: 3.13
Classifier: Topic :: Text Processing :: Filters
Classifier: Topic :: Software Development :: Documentation
Requires-Python: >=3.8
License-File: LICENSE
Requires-Dist: panflute>=2.0.0
Requires-Dist: jinja2>=3.0.0
Requires-Dist: pandas>=1.0.0
Requires-Dist: pyyaml>=5.0.0
Requires-Dist: tomli>=1.0.0; python_version < "3.11"
Requires-Dist: regex>=2024.11.6
Dynamic: license-file
